springheel/__init__.py
springheel/acopy.py
springheel/addimg.py
springheel/classes.py
springheel/command_line.py
springheel/conf.ini
springheel/copystuff.py
springheel/genabout.py
springheel/genchars.py
springheel/genchbook.py
springheel/generatearchive.py
springheel/generatenav.py
springheel/genextra.py
springheel/genjsonfeed.py
springheel/genmultilang.py
springheel/genmultipleindex.py
springheel/genrss.py
springheel/genstatline.py
springheel/gentopnav.py
springheel/gentrans.py
springheel/gettemplatenames.py
springheel/metatag.py
springheel/parseconf.py
springheel/parsemeta.py
springheel/parsetranscript.py
springheel/renameimgs.py
springheel/slugurl.py
springheel/socialbuttons.py
springheel/splitseps.py
springheel/springheelinit.py
springheel/tl.py
springheel/webtoon.py
springheel/wraptag.py
springheel/__pycache__/__init__.cpython-38.pyc
springheel/__pycache__/__init__.cpython-39.pyc
springheel/__pycache__/__main__.cpython-39.pyc
springheel/__pycache__/acopy.cpython-39.pyc
springheel/__pycache__/addimg.cpython-39.pyc
springheel/__pycache__/classes.cpython-39.pyc
springheel/__pycache__/command_line.cpython-39.pyc
springheel/__pycache__/copystuff.cpython-39.pyc
springheel/__pycache__/genabout.cpython-39.pyc
springheel/__pycache__/genchars.cpython-38.pyc
springheel/__pycache__/genchars.cpython-39.pyc
springheel/__pycache__/genchbook.cpython-38.pyc
springheel/__pycache__/genchbook.cpython-39.pyc
springheel/__pycache__/generatearchive.cpython-38.pyc
springheel/__pycache__/generatearchive.cpython-39.pyc
springheel/__pycache__/generatenav.cpython-38.pyc
springheel/__pycache__/generatenav.cpython-39.pyc
springheel/__pycache__/genextra.cpython-38.pyc
springheel/__pycache__/genextra.cpython-39.pyc
springheel/__pycache__/genjsonfeed.cpython-38.pyc
springheel/__pycache__/genjsonfeed.cpython-39.pyc
springheel/__pycache__/genmultilang.cpython-38.pyc
springheel/__pycache__/genmultilang.cpython-39.pyc
springheel/__pycache__/genmultipleindex.cpython-38.pyc
springheel-7.0.2.dist-info/AUTHORS
springheel-7.0.2.dist-info/LICENSE
springheel-7.0.2.dist-info/METADATA
springheel-7.0.2.dist-info/WHEEL
springheel-7.0.2.dist-info/entry_points.txt
springheel-7.0.2.dist-info/top_level.txt
springheel-7.0.2.dist-info/RECORD
