Metadata-Version: 2.1
Name: springheel
Version: 7.0.2
Summary: Static site generator for webcomics
Home-page: https://www.twinkle-night.net/Code/springheel.html
Author: Garrick
Author-email: earthisthering@posteo.de
License: GPLv3+
Keywords: website,webcomic,static
Platform: UNKNOWN
Classifier: Development Status :: 4 - Beta
Classifier: License :: OSI Approved :: GNU General Public License v3 or later (GPLv3+)
Classifier: Programming Language :: Python :: 3
Classifier: Intended Audience :: End Users/Desktop
Classifier: Topic :: Internet
Requires-Dist: feedgen
Requires-Dist: python-slugify
Requires-Dist: tqdm
Requires-Dist: html-sanitizer
Requires-Dist: Pillow
Provides-Extra: docs
Requires-Dist: sphinx (>=3.4.1) ; extra == 'docs'
Requires-Dist: numpydoc ; extra == 'docs'
